outputscouting/__init__.py
outputscouting/_command.py
outputscouting/_extensive_search.py
outputscouting/_loader.py
outputscouting/_min_dependencies.py
outputscouting/_scout.py
outputscouting/_temp_setter.py
outputscouting/_version.py
outputscouting/_visualization.py
outputscouting/base.py
outputscouting-0.1.1.dist-info/LICENSE
outputscouting-0.1.1.dist-info/METADATA
outputscouting-0.1.1.dist-info/WHEEL
outputscouting-0.1.1.dist-info/top_level.txt
outputscouting-0.1.1.dist-info/RECORD
